{"meta":{"version":1,"warehouse":"4.0.2"},"models":{"Asset":[{"_id":"themes/tkl/source/css/all.styl","path":"css/all.styl","modified":0,"renderable":1},{"_id":"themes/tkl/source/css/bootstrap.min.css","path":"css/bootstrap.min.css","modified":0,"renderable":1},{"_id":"themes/tkl/source/css/animate.css","path":"css/animate.css","modified":0,"renderable":1},{"_id":"themes/tkl/source/css/animsition.min.css","path":"css/animsition.min.css","modified":0,"renderable":1},{"_id":"themes/tkl/source/css/custom.css","path":"css/custom.css","modified":0,"renderable":1},{"_id":"themes/tkl/source/css/flexslider.css","path":"css/flexslider.css","modified":0,"renderable":1},{"_id":"themes/tkl/source/css/ie8.css","path":"css/ie8.css","modified":0,"renderable":1},{"_id":"themes/tkl/source/css/iconList.css","path":"css/iconList.css","modified":0,"renderable":1},{"_id":"themes/tkl/source/css/screen.css","path":"css/screen.css","modified":0,"renderable":1},{"_id":"themes/tkl/source/css/style.css","path":"css/style.css","modified":0,"renderable":1},{"_id":"themes/tkl/source/css/slidebars.min.css","path":"css/slidebars.min.css","modified":0,"renderable":1},{"_id":"themes/tkl/source/css/syntax.styl","path":"css/syntax.styl","modified":0,"renderable":1},{"_id":"themes/tkl/source/fancybox/blank.gif","path":"fancybox/blank.gif","modified":0,"renderable":1},{"_id":"themes/tkl/source/fancybox/fancybox_loading.gif","path":"fancybox/fancybox_loading.gif","modified":0,"renderable":1},{"_id":"themes/tkl/source/fancybox/fancybox_loading@2x.gif","path":"fancybox/fancybox_loading@2x.gif","modified":0,"renderable":1},{"_id":"themes/tkl/source/fancybox/fancybox_overlay.png","path":"fancybox/fancybox_overlay.png","modified":0,"renderable":1},{"_id":"themes/tkl/source/fancybox/fancybox_sprite.png","path":"fancybox/fancybox_sprite.png","modified":0,"renderable":1},{"_id":"themes/tkl/source/fancybox/fancybox_sprite@2x.png","path":"fancybox/fancybox_sprite@2x.png","modified":0,"renderable":1},{"_id":"themes/tkl/source/fancybox/jquery.fancybox.css","path":"fancybox/jquery.fancybox.css","modified":0,"renderable":1},{"_id":"themes/tkl/source/fancybox/jquery.fancybox.pack.js","path":"fancybox/jquery.fancybox.pack.js","modified":0,"renderable":1},{"_id":"themes/tkl/source/highlightjs/arta.css","path":"highlightjs/arta.css","modified":0,"renderable":1},{"_id":"themes/tkl/source/highlightjs/brown_paper.css","path":"highlightjs/brown_paper.css","modified":0,"renderable":1},{"_id":"themes/tkl/source/highlightjs/brown_papersq.png","path":"highlightjs/brown_papersq.png","modified":0,"renderable":1},{"_id":"themes/tkl/source/highlightjs/ascetic.css","path":"highlightjs/ascetic.css","modified":0,"renderable":1},{"_id":"themes/tkl/source/highlightjs/dark.css","path":"highlightjs/dark.css","modified":0,"renderable":1},{"_id":"themes/tkl/source/highlightjs/default.css","path":"highlightjs/default.css","modified":0,"renderable":1},{"_id":"themes/tkl/source/highlightjs/docco.css","path":"highlightjs/docco.css","modified":0,"renderable":1},{"_id":"themes/tkl/source/highlightjs/far.css","path":"highlightjs/far.css","modified":0,"renderable":1},{"_id":"themes/tkl/source/highlightjs/foundation.css","path":"highlightjs/foundation.css","modified":0,"renderable":1},{"_id":"themes/tkl/source/highlightjs/github.css","path":"highlightjs/github.css","modified":0,"renderable":1},{"_id":"themes/tkl/source/highlightjs/googlecode.css","path":"highlightjs/googlecode.css","modified":0,"renderable":1},{"_id":"themes/tkl/source/highlightjs/idea.css","path":"highlightjs/idea.css","modified":0,"renderable":1},{"_id":"themes/tkl/source/highlightjs/mono-blue.css","path":"highlightjs/mono-blue.css","modified":0,"renderable":1},{"_id":"themes/tkl/source/highlightjs/magula.css","path":"highlightjs/magula.css","modified":0,"renderable":1},{"_id":"themes/tkl/source/highlightjs/monokai.css","path":"highlightjs/monokai.css","modified":0,"renderable":1},{"_id":"themes/tkl/source/highlightjs/ir_black.css","path":"highlightjs/ir_black.css","modified":0,"renderable":1},{"_id":"themes/tkl/source/highlightjs/monokai_sublime.css","path":"highlightjs/monokai_sublime.css","modified":0,"renderable":1},{"_id":"themes/tkl/source/highlightjs/pojoaque.css","path":"highlightjs/pojoaque.css","modified":0,"renderable":1},{"_id":"themes/tkl/source/highlightjs/pojoaque.jpg","path":"highlightjs/pojoaque.jpg","modified":0,"renderable":1},{"_id":"themes/tkl/source/highlightjs/obsidian.css","path":"highlightjs/obsidian.css","modified":0,"renderable":1},{"_id":"themes/tkl/source/highlightjs/railscasts.css","path":"highlightjs/railscasts.css","modified":0,"renderable":1},{"_id":"themes/tkl/source/highlightjs/school_book.css","path":"highlightjs/school_book.css","modified":0,"renderable":1},{"_id":"themes/tkl/source/highlightjs/rainbow.css","path":"highlightjs/rainbow.css","modified":0,"renderable":1},{"_id":"themes/tkl/source/highlightjs/solarized_dark.css","path":"highlightjs/solarized_dark.css","modified":0,"renderable":1},{"_id":"themes/tkl/source/highlightjs/school_book.png","path":"highlightjs/school_book.png","modified":0,"renderable":1},{"_id":"themes/tkl/source/highlightjs/sunburst.css","path":"highlightjs/sunburst.css","modified":0,"renderable":1},{"_id":"themes/tkl/source/highlightjs/solarized_light.css","path":"highlightjs/solarized_light.css","modified":0,"renderable":1},{"_id":"themes/tkl/source/highlightjs/tomorrow-night-blue.css","path":"highlightjs/tomorrow-night-blue.css","modified":0,"renderable":1},{"_id":"themes/tkl/source/highlightjs/tomorrow-night-bright.css","path":"highlightjs/tomorrow-night-bright.css","modified":0,"renderable":1},{"_id":"themes/tkl/source/highlightjs/tomorrow-night-eighties.css","path":"highlightjs/tomorrow-night-eighties.css","modified":0,"renderable":1},{"_id":"themes/tkl/source/highlightjs/tomorrow-night.css","path":"highlightjs/tomorrow-night.css","modified":0,"renderable":1},{"_id":"themes/tkl/source/highlightjs/tomorrow.css","path":"highlightjs/tomorrow.css","modified":0,"renderable":1},{"_id":"themes/tkl/source/highlightjs/vs.css","path":"highlightjs/vs.css","modified":0,"renderable":1},{"_id":"themes/tkl/source/highlightjs/xcode.css","path":"highlightjs/xcode.css","modified":0,"renderable":1},{"_id":"themes/tkl/source/img/1313 - Men's Boots.png","path":"img/1313 - Men's Boots.png","modified":0,"renderable":1},{"_id":"themes/tkl/source/highlightjs/zenburn.css","path":"highlightjs/zenburn.css","modified":0,"renderable":1},{"_id":"themes/tkl/source/img/1313 - Men's Boots.ico","path":"img/1313 - Men's Boots.ico","modified":0,"renderable":1},{"_id":"themes/tkl/source/img/1314 - Casual Shoes.ico","path":"img/1314 - Casual Shoes.ico","modified":0,"renderable":1},{"_id":"themes/tkl/source/img/1314 - Casual Shoes.png","path":"img/1314 - Casual Shoes.png","modified":0,"renderable":1},{"_id":"themes/tkl/source/img/banner-1566213_640.jpg","path":"img/banner-1566213_640.jpg","modified":0,"renderable":1},{"_id":"themes/tkl/source/img/close.png","path":"img/close.png","modified":0,"renderable":1},{"_id":"themes/tkl/source/img/banner-1559392_640.jpg","path":"img/banner-1559392_640.jpg","modified":0,"renderable":1},{"_id":"themes/tkl/source/img/favicon.ico","path":"img/favicon.ico","modified":0,"renderable":1},{"_id":"themes/tkl/source/fonts/icons.svg","path":"fonts/icons.svg","modified":0,"renderable":1},{"_id":"themes/tkl/source/fonts/icons.ttf","path":"fonts/icons.ttf","modified":0,"renderable":1},{"_id":"themes/tkl/source/fonts/icons.woff","path":"fonts/icons.woff","modified":0,"renderable":1},{"_id":"themes/tkl/source/fonts/icons.eot","path":"fonts/icons.eot","modified":0,"renderable":1},{"_id":"themes/tkl/source/fonts/opensans.woff","path":"fonts/opensans.woff","modified":0,"renderable":1},{"_id":"themes/tkl/source/js/html5shiv.min.js","path":"js/html5shiv.min.js","modified":0,"renderable":1},{"_id":"themes/tkl/source/js/jquery-1.11.1.min.js","path":"js/jquery-1.11.1.min.js","modified":0,"renderable":1},{"_id":"themes/tkl/source/js/jquery.flexslider-min.js","path":"js/jquery.flexslider-min.js","modified":0,"renderable":1},{"_id":"themes/tkl/source/js/jquery.ajaxchimp.min.js","path":"js/jquery.ajaxchimp.min.js","modified":0,"renderable":1},{"_id":"themes/tkl/source/js/plugins.min.js","path":"js/plugins.min.js","modified":0,"renderable":1},{"_id":"themes/tkl/source/js/respond.min.js","path":"js/respond.min.js","modified":0,"renderable":1},{"_id":"themes/tkl/source/js/scripts.js","path":"js/scripts.js","modified":0,"renderable":1},{"_id":"themes/tkl/source/js/ziploader.js","path":"js/ziploader.js","modified":0,"renderable":1}],"Cache":[{"_id":"source/categories/index.md","hash":"23d3aa3d3cee11ddae392b8e5f19a8374d8de5dd","modified":1660569820880},{"_id":"source/_posts/What-are-the-10-easy-ways-to-make-your-dog-more-comfortable-at-home.md","hash":"2c76813c4c55f96cde6857f9a2075da56a53bd99","modified":1660569852417},{"_id":"source/tags/index.md","hash":"53af70412d9c664c5996fd7ed3280e583c85d685","modified":1660569823067},{"_id":"themes/tkl/layout/index.ejs","hash":"36e89b37f520533bef85fb32b714214257fad1d0","modified":1650768698000},{"_id":"themes/tkl/README.md","hash":"be19038e1bde09ad060e20b645e4d22df37eec1d","modified":1650768698000},{"_id":"themes/tkl/LICENSE","hash":"c700a8b9312d24bdc57570f7d6a131cf63d89016","modified":1650768698000},{"_id":"themes/tkl/custom.json","hash":"753487dd9d66f127038655443e120ec07d49b0cd","modified":1660299250000},{"_id":"themes/tkl/layout/layout.ejs","hash":"bf860625a18dd23d4e7064a80e3df0f19d9784ad","modified":1650768698000},{"_id":"themes/tkl/_config.yml","hash":"db4b4672bff0a7703a29ea45e34fbcbb2c8458ea","modified":1663572141260},{"_id":"themes/tkl/layout/category.ejs","hash":"9b740fc33f6f028df60f0bc4312bf3ebd03aa8ea","modified":1650768698000},{"_id":"themes/tkl/layout/page.ejs","hash":"29cf5f3bb27821cec6dd59d90ca1604b32f8fc0c","modified":1650768698000},{"_id":"themes/tkl/layout/post.ejs","hash":"ae761feddc98f4d3260e7591ed9fc91d9a49d0ab","modified":1650768698000},{"_id":"themes/tkl/layout/archive.ejs","hash":"a18842e3d719fe3ca9b977a6995f8facc75c8673","modified":1650768698000},{"_id":"themes/tkl/layout/tag.ejs","hash":"45150a2365768b6b67880193c9264ad2bb4814db","modified":1650768698000},{"_id":"themes/tkl/layout/_partial/about.ejs","hash":"b0127ff072ce3158cc59301da9322c7dd9fd3a7d","modified":1650768698000},{"_id":"themes/tkl/layout/_partial/head.ejs","hash":"a3df7f3635b130c29da429dbd450848fbb59e542","modified":1660299634000},{"_id":"themes/tkl/layout/_partial/footer.ejs","hash":"e19d4ed9e94c73bf113663ef69d7d57671b59241","modified":1663642481702},{"_id":"themes/tkl/layout/_partial/after_all.ejs","hash":"706f9dd71442877349b53d360d42eb68cbb4856f","modified":1650768698000},{"_id":"themes/tkl/layout/_partial/archive.ejs","hash":"be083c1c5f865f64efbf9a17b34e5ccbe0bb9d64","modified":1650768698000},{"_id":"themes/tkl/layout/_partial/header.ejs","hash":"50bbe660ba2bf5dc0eb2b2c557fd3b80f5fd326b","modified":1660294250000},{"_id":"themes/tkl/layout/_partial/post.ejs","hash":"049c265fa02f69303f48753ae342ec2f65b9bb92","modified":1650768698000},{"_id":"themes/tkl/layout/_partial/search.ejs","hash":"e6be2c6ef3b4d560c2b6291630e6ae1e6674c1bc","modified":1650768698000},{"_id":"themes/tkl/layout/_partial/index.ejs","hash":"461d0772d383da6c6e3ed88e93f399f02002121a","modified":1650768698000},{"_id":"themes/tkl/source/css/all.styl","hash":"9fa61a7eda4ea10ac7aac6ac438de96c3be3c487","modified":1650768698000},{"_id":"themes/tkl/source/css/animate.css","hash":"fca75b84887199a0ed8e0f056ff30f5a1302f324","modified":1650768698000},{"_id":"themes/tkl/source/css/animsition.min.css","hash":"59033074f6594a0d87c759e2b8cf9baa3a62ed6a","modified":1650768698000},{"_id":"themes/tkl/source/css/custom.css","hash":"e87423888bf9a13ee0bc28a5aa725f40f999608a","modified":1650768698000},{"_id":"themes/tkl/source/css/flexslider.css","hash":"faebc8c54ca41e3c9936edaffbabbebd512c6d5a","modified":1650768698000},{"_id":"themes/tkl/source/css/ie8.css","hash":"cfdfe07ecc9f3afa5bab47155b49f0924f62d2c2","modified":1650768698000},{"_id":"themes/tkl/source/css/iconList.css","hash":"f78ffffb4be40a6b0eb6ee109c958ccd062d1ae5","modified":1650768698000},{"_id":"themes/tkl/source/css/slidebars.min.css","hash":"a802c15d9bf06005b463901be8325d8ce38b5b04","modified":1650768698000},{"_id":"themes/tkl/source/css/syntax.styl","hash":"f39ea1e483c9244f39003d3efd20deb535ecddc7","modified":1650768698000},{"_id":"themes/tkl/source/css/screen.css","hash":"a13c2c6fe420f76083df2da6d7b2d765dd8b467e","modified":1650768698000},{"_id":"themes/tkl/source/fancybox/blank.gif","hash":"2daeaa8b5f19f0bc209d976c02bd6acb51b00b0a","modified":1650768698000},{"_id":"themes/tkl/source/fancybox/fancybox_loading.gif","hash":"1a755fb2599f3a313cc6cfdb14df043f8c14a99c","modified":1650768698000},{"_id":"themes/tkl/source/fancybox/fancybox_loading@2x.gif","hash":"273b123496a42ba45c3416adb027cd99745058b0","modified":1650768698000},{"_id":"themes/tkl/source/fancybox/fancybox_overlay.png","hash":"b3a4ee645ba494f52840ef8412015ba0f465dbe0","modified":1650768698000},{"_id":"themes/tkl/source/fancybox/fancybox_sprite.png","hash":"17df19f97628e77be09c352bf27425faea248251","modified":1650768698000},{"_id":"themes/tkl/source/fancybox/fancybox_sprite@2x.png","hash":"30c58913f327e28f466a00f4c1ac8001b560aed8","modified":1650768698000},{"_id":"themes/tkl/source/fancybox/jquery.fancybox.css","hash":"5f163444617b6cf267342f06ac166a237bb62df9","modified":1650768698000},{"_id":"themes/tkl/source/highlightjs/arta.css","hash":"08766ac9d70bde457fea9c553140029f57ace65a","modified":1650768698000},{"_id":"themes/tkl/source/fancybox/jquery.fancybox.pack.js","hash":"53360764b429c212f424399384417ccc233bb3be","modified":1650768698000},{"_id":"themes/tkl/source/highlightjs/brown_paper.css","hash":"2a987d30dd142a5c316ace70e919e3312707ebbd","modified":1650768698000},{"_id":"themes/tkl/source/highlightjs/brown_papersq.png","hash":"3a1332ede3a75a3d24f60b6ed69035b72da5e182","modified":1650768698000},{"_id":"themes/tkl/source/highlightjs/ascetic.css","hash":"dd5e0c6c11bc199884cc5abf7310e79ce8018d0d","modified":1650768698000},{"_id":"themes/tkl/source/highlightjs/dark.css","hash":"38045930b1d862bb6e14960e94e63782145a598f","modified":1650768698000},{"_id":"themes/tkl/source/highlightjs/default.css","hash":"108ad8410aa3004eafc452ae60771a2ae24d7988","modified":1650768698000},{"_id":"themes/tkl/source/highlightjs/docco.css","hash":"70199b44d688d0a22851bd5481260f24160a38ee","modified":1650768698000},{"_id":"themes/tkl/source/highlightjs/foundation.css","hash":"308c2e0458fc117b323f7d9ce1644f7b4e52d99e","modified":1650768698000},{"_id":"themes/tkl/source/highlightjs/far.css","hash":"8178ac70abe577ae8345f1f6291bf7d489ad384d","modified":1650768698000},{"_id":"themes/tkl/source/highlightjs/github.css","hash":"53f47e65e6e0e6068baf5c4b638b04d2f4e0b0bc","modified":1650768698000},{"_id":"themes/tkl/source/highlightjs/idea.css","hash":"fb77c293850c454c1f0c72628c0b301537765ad2","modified":1650768698000},{"_id":"themes/tkl/source/highlightjs/googlecode.css","hash":"731e74bcdfd1b68aae5b5805540f727c31309ba2","modified":1650768698000},{"_id":"themes/tkl/source/highlightjs/magula.css","hash":"5666f49986f05fb8956e0c3065a383b252779442","modified":1650768698000},{"_id":"themes/tkl/source/highlightjs/ir_black.css","hash":"2da52e8562b412039b5816e1a3a2f59e7dff0c27","modified":1650768698000},{"_id":"themes/tkl/source/highlightjs/mono-blue.css","hash":"c143e9d8c62dc71ca39bc0b6c127464ed2396e4f","modified":1650768698000},{"_id":"themes/tkl/source/highlightjs/monokai.css","hash":"a0edb8327c191516a04d456db8aae9044055a5cf","modified":1650768698000},{"_id":"themes/tkl/source/highlightjs/monokai_sublime.css","hash":"6b4716416b1bba643d3a7926221ce6d83a139141","modified":1650768698000},{"_id":"themes/tkl/source/highlightjs/pojoaque.css","hash":"c9b048dc71c5b45d5cb3daac8f332a7e5d13b20f","modified":1650768698000},{"_id":"themes/tkl/source/highlightjs/pojoaque.jpg","hash":"c5fe6533b88b21f8d90d3d03954c6b29baa67791","modified":1650768698000},{"_id":"themes/tkl/source/highlightjs/obsidian.css","hash":"d6c264e1973beb9f20001b9a4013e9983923b34e","modified":1650768698000},{"_id":"themes/tkl/source/highlightjs/school_book.css","hash":"f257d41cdca2609fa4c664df9cc14b48e2bcb09f","modified":1650768698000},{"_id":"themes/tkl/source/highlightjs/rainbow.css","hash":"b0e18f0f7fa08d5ad11956e2d9cc5e2ffdd514f3","modified":1650768698000},{"_id":"themes/tkl/source/highlightjs/solarized_dark.css","hash":"007f9f1e7addf7e2040734cd1f733d041432c335","modified":1650768698000},{"_id":"themes/tkl/source/highlightjs/railscasts.css","hash":"aeb6ecd79552b9611d447fe56de5266954ea055c","modified":1650768698000},{"_id":"themes/tkl/source/highlightjs/school_book.png","hash":"711ec983c874e093bb89eb77afcbdf6741fa61ee","modified":1650768698000},{"_id":"themes/tkl/source/highlightjs/sunburst.css","hash":"e72bc116795505c1fcae35bc69045043fc34a243","modified":1650768698000},{"_id":"themes/tkl/source/highlightjs/solarized_light.css","hash":"a85878fd70ecd03c71944df1acbbf320bac7979f","modified":1650768698000},{"_id":"themes/tkl/source/highlightjs/tomorrow-night-blue.css","hash":"e2bed22abcdf3f2b8ca3a1a73624751d3edc4e64","modified":1650768698000},{"_id":"themes/tkl/source/highlightjs/tomorrow-night-bright.css","hash":"afdb004743a8d2b52d38c7a1fce32d631a0f3ded","modified":1650768698000},{"_id":"themes/tkl/source/highlightjs/tomorrow-night.css","hash":"48cd18ce93daa491d89eb63e5fe3ab640ff56d74","modified":1650768698000},{"_id":"themes/tkl/source/highlightjs/tomorrow-night-eighties.css","hash":"9603bc778de2dabd0ce1e7ee272a047338a8b99c","modified":1650768698000},{"_id":"themes/tkl/source/highlightjs/tomorrow.css","hash":"a184e23b28b6a6401ecfc35e0a94de0bada589e4","modified":1650768698000},{"_id":"themes/tkl/source/highlightjs/vs.css","hash":"13e2f7ec2e197d79f4fc36768ea4a0663d41e1c0","modified":1650768698000},{"_id":"themes/tkl/source/img/1313 - Men's Boots.png","hash":"9d86347d6d4cc06640d9e74f925e94954ca6a357","modified":1660525698000},{"_id":"themes/tkl/source/highlightjs/zenburn.css","hash":"73dafd21563f5fc3bb74856d4abf97c447a27772","modified":1650768698000},{"_id":"themes/tkl/source/highlightjs/xcode.css","hash":"78cb5758ce4085aa51edb6c5beb64d8f4511edd7","modified":1650768698000},{"_id":"themes/tkl/source/img/1314 - Casual Shoes.png","hash":"7ba165c1417b5fb7e4929e1c17afb503bfa0e7da","modified":1660525700000},{"_id":"themes/tkl/source/img/banner-1566213_640.jpg","hash":"afdf9bd10023255c2f63e47e0130b324a551df6f","modified":1660559429330},{"_id":"themes/tkl/source/img/1313 - Men's Boots.ico","hash":"9d86347d6d4cc06640d9e74f925e94954ca6a357","modified":1660569818555},{"_id":"themes/tkl/source/img/1314 - Casual Shoes.ico","hash":"7ba165c1417b5fb7e4929e1c17afb503bfa0e7da","modified":1660569818576},{"_id":"themes/tkl/source/img/close.png","hash":"e52e6a61877efd98ddad9ca31ece27e8ee977327","modified":1650768698000},{"_id":"themes/tkl/source/img/banner-1559392_640.jpg","hash":"73acf64b1390bec127a4dc29c7d1bace9569f689","modified":1660559317120},{"_id":"themes/tkl/source/img/favicon.ico","hash":"70fbd67d92be00781652fed26bda9af8d931fb0a","modified":1650768698000},{"_id":"themes/tkl/source/fonts/icons.ttf","hash":"2169592997f694ffa05b1d4c23d5a1abf35d3203","modified":1650768698000},{"_id":"themes/tkl/source/fonts/icons.woff","hash":"af538de6ac19d5da1cada203c7451ce32f5daceb","modified":1650768698000},{"_id":"themes/tkl/source/fonts/icons.eot","hash":"e307fc2d61d13bbc3aafc9abd75e727cbebadee1","modified":1650768698000},{"_id":"themes/tkl/source/fonts/opensans.woff","hash":"43b78d92be59efafc7ada7ee21abd4ba7a65c663","modified":1650768698000},{"_id":"themes/tkl/source/js/html5shiv.min.js","hash":"bb51a5f6c394989bb06e4171179354c6d05ec8f8","modified":1650768698000},{"_id":"themes/tkl/source/js/jquery.ajaxchimp.min.js","hash":"9be17785b0d816e1cd6bc45908e1805e0522fe18","modified":1650768698000},{"_id":"themes/tkl/source/js/jquery.flexslider-min.js","hash":"51b3a7d882f438d53dc69ca5289e92254160c09a","modified":1650768698000},{"_id":"themes/tkl/source/js/respond.min.js","hash":"b5aba40d65b0d6f85859db47f757ea971a0efd30","modified":1650768698000},{"_id":"themes/tkl/source/js/ziploader.js","hash":"4d487998f85dc6fae6c29c94f0163aa4c309319f","modified":1650768698000},{"_id":"themes/tkl/source/js/scripts.js","hash":"9c05b2538f02df0313e6892083d2716d2c258f49","modified":1650768698000},{"_id":"themes/tkl/layout/_partial/post/navigation.ejs","hash":"1dd81ccccc3125d821765cfef1889bd25e85b5d5","modified":1650768698000},{"_id":"themes/tkl/layout/_partial/post/comments.ejs","hash":"b42d96dc6e14558d31224a10149e2ac104f2da0e","modified":1650768698000},{"_id":"themes/tkl/layout/_partial/post/meta.ejs","hash":"c984cdc774bc884b33c8d87e3b59728cfdee773c","modified":1650768698000},{"_id":"themes/tkl/source/css/bootstrap.min.css","hash":"aabbadd6b436fa24c84fd8ca01d433bdab26fba5","modified":1650768698000},{"_id":"themes/tkl/source/css/style.css","hash":"4b2f1e4d1e2ac78454691c7980b6e785979f4218","modified":1660297982000},{"_id":"themes/tkl/source/fonts/icons.svg","hash":"4b8357c608c01f304789e34bfd133081c1fc8b9d","modified":1650768698000},{"_id":"themes/tkl/source/js/jquery-1.11.1.min.js","hash":"d6c1f41972de07b09bfa63d2e50f9ab41ec372bd","modified":1650768698000},{"_id":"themes/tkl/source/js/plugins.min.js","hash":"b9c5dd602b0d25d02ad704eef6e4e4d3b25f78db","modified":1650768698000},{"_id":"public/categories/index.html","hash":"bffd158fd6be7a2c04e46a8a3aae57ae08fc5d6e","modified":1663642483071},{"_id":"public/tags/index.html","hash":"fbb13e93acf9ecdff421a2e668b37ce2be6647eb","modified":1663642483071},{"_id":"public/2022/08/15/What-are-the-10-easy-ways-to-make-your-dog-more-comfortable-at-home/index.html","hash":"dc5210dbc4ad2b3533bbf7c382a114124f8e3382","modified":1663642483071},{"_id":"public/categories/Dog-Park/index.html","hash":"86ed146647d5506a9a0c3801d5a3101a5e8b72fe","modified":1663642483071},{"_id":"public/archives/index.html","hash":"50851b1a99eb30106bc230e49f0dc7b099b4d1c2","modified":1663642483071},{"_id":"public/index.html","hash":"9ed3f33b9e221d6b4398a25d3dd8724c33980a82","modified":1663642483071},{"_id":"public/archives/2022/index.html","hash":"7f84f0690bcc7d47205fe0bd37891dfe8c1dac99","modified":1663642483071},{"_id":"public/archives/2022/08/index.html","hash":"1aecbe1253c128c9d5eed6d40c504637299638b4","modified":1663642483071},{"_id":"public/fancybox/blank.gif","hash":"2daeaa8b5f19f0bc209d976c02bd6acb51b00b0a","modified":1660569854091},{"_id":"public/fancybox/fancybox_loading@2x.gif","hash":"273b123496a42ba45c3416adb027cd99745058b0","modified":1660569854091},{"_id":"public/fancybox/fancybox_overlay.png","hash":"b3a4ee645ba494f52840ef8412015ba0f465dbe0","modified":1660569854091},{"_id":"public/fancybox/fancybox_loading.gif","hash":"1a755fb2599f3a313cc6cfdb14df043f8c14a99c","modified":1660569854091},{"_id":"public/fancybox/fancybox_sprite.png","hash":"17df19f97628e77be09c352bf27425faea248251","modified":1660569854091},{"_id":"public/fancybox/fancybox_sprite@2x.png","hash":"30c58913f327e28f466a00f4c1ac8001b560aed8","modified":1660569854091},{"_id":"public/highlightjs/school_book.png","hash":"711ec983c874e093bb89eb77afcbdf6741fa61ee","modified":1660569854091},{"_id":"public/highlightjs/pojoaque.jpg","hash":"c5fe6533b88b21f8d90d3d03954c6b29baa67791","modified":1660569854091},{"_id":"public/img/1313 - Men's Boots.png","hash":"9d86347d6d4cc06640d9e74f925e94954ca6a357","modified":1660569854091},{"_id":"public/highlightjs/brown_papersq.png","hash":"3a1332ede3a75a3d24f60b6ed69035b72da5e182","modified":1660569854091},{"_id":"public/img/1314 - Casual Shoes.png","hash":"7ba165c1417b5fb7e4929e1c17afb503bfa0e7da","modified":1660569854091},{"_id":"public/img/1313 - Men's Boots.ico","hash":"9d86347d6d4cc06640d9e74f925e94954ca6a357","modified":1660569854091},{"_id":"public/img/banner-1566213_640.jpg","hash":"afdf9bd10023255c2f63e47e0130b324a551df6f","modified":1660569854091},{"_id":"public/img/1314 - Casual Shoes.ico","hash":"7ba165c1417b5fb7e4929e1c17afb503bfa0e7da","modified":1660569854091},{"_id":"public/img/banner-1559392_640.jpg","hash":"73acf64b1390bec127a4dc29c7d1bace9569f689","modified":1660569854091},{"_id":"public/img/close.png","hash":"e52e6a61877efd98ddad9ca31ece27e8ee977327","modified":1660569854091},{"_id":"public/img/favicon.ico","hash":"70fbd67d92be00781652fed26bda9af8d931fb0a","modified":1660569854091},{"_id":"public/fonts/icons.ttf","hash":"2169592997f694ffa05b1d4c23d5a1abf35d3203","modified":1660569854091},{"_id":"public/fonts/icons.woff","hash":"af538de6ac19d5da1cada203c7451ce32f5daceb","modified":1660569854091},{"_id":"public/fonts/icons.eot","hash":"e307fc2d61d13bbc3aafc9abd75e727cbebadee1","modified":1660569854091},{"_id":"public/fonts/opensans.woff","hash":"43b78d92be59efafc7ada7ee21abd4ba7a65c663","modified":1660569854091},{"_id":"public/css/custom.css","hash":"e87423888bf9a13ee0bc28a5aa725f40f999608a","modified":1660569854091},{"_id":"public/css/animate.css","hash":"fca75b84887199a0ed8e0f056ff30f5a1302f324","modified":1660569854091},{"_id":"public/css/ie8.css","hash":"cfdfe07ecc9f3afa5bab47155b49f0924f62d2c2","modified":1660569854091},{"_id":"public/css/flexslider.css","hash":"faebc8c54ca41e3c9936edaffbabbebd512c6d5a","modified":1660569854091},{"_id":"public/css/screen.css","hash":"a13c2c6fe420f76083df2da6d7b2d765dd8b467e","modified":1660569854091},{"_id":"public/css/iconList.css","hash":"f78ffffb4be40a6b0eb6ee109c958ccd062d1ae5","modified":1660569854091},{"_id":"public/css/slidebars.min.css","hash":"a802c15d9bf06005b463901be8325d8ce38b5b04","modified":1660569854091},{"_id":"public/css/syntax.css","hash":"d5923a6251a113ac02916bcd1119356bd780d7ef","modified":1660569854091},{"_id":"public/highlightjs/arta.css","hash":"08766ac9d70bde457fea9c553140029f57ace65a","modified":1660569854091},{"_id":"public/fancybox/jquery.fancybox.css","hash":"5f163444617b6cf267342f06ac166a237bb62df9","modified":1660569854091},{"_id":"public/highlightjs/brown_paper.css","hash":"2a987d30dd142a5c316ace70e919e3312707ebbd","modified":1660569854091},{"_id":"public/highlightjs/ascetic.css","hash":"ef259aecdc8f1367dcf890d6467369300c4c0d07","modified":1660569854091},{"_id":"public/highlightjs/dark.css","hash":"2c2b4eb2562d812d95a26da0ffae51371b383713","modified":1660569854091},{"_id":"public/highlightjs/docco.css","hash":"70199b44d688d0a22851bd5481260f24160a38ee","modified":1660569854091},{"_id":"public/highlightjs/foundation.css","hash":"308c2e0458fc117b323f7d9ce1644f7b4e52d99e","modified":1660569854091},{"_id":"public/highlightjs/far.css","hash":"8178ac70abe577ae8345f1f6291bf7d489ad384d","modified":1660569854091},{"_id":"public/highlightjs/default.css","hash":"108ad8410aa3004eafc452ae60771a2ae24d7988","modified":1660569854091},{"_id":"public/highlightjs/googlecode.css","hash":"731e74bcdfd1b68aae5b5805540f727c31309ba2","modified":1660569854091},{"_id":"public/highlightjs/idea.css","hash":"fb77c293850c454c1f0c72628c0b301537765ad2","modified":1660569854091},{"_id":"public/highlightjs/magula.css","hash":"9c53982a77259331c1dc3b24ef744dd76b3fe643","modified":1660569854091},{"_id":"public/highlightjs/github.css","hash":"53f47e65e6e0e6068baf5c4b638b04d2f4e0b0bc","modified":1660569854091},{"_id":"public/highlightjs/ir_black.css","hash":"2da52e8562b412039b5816e1a3a2f59e7dff0c27","modified":1660569854091},{"_id":"public/highlightjs/mono-blue.css","hash":"c143e9d8c62dc71ca39bc0b6c127464ed2396e4f","modified":1660569854091},{"_id":"public/highlightjs/pojoaque.css","hash":"c9b048dc71c5b45d5cb3daac8f332a7e5d13b20f","modified":1660569854091},{"_id":"public/highlightjs/monokai_sublime.css","hash":"6b4716416b1bba643d3a7926221ce6d83a139141","modified":1660569854091},{"_id":"public/highlightjs/obsidian.css","hash":"d6c264e1973beb9f20001b9a4013e9983923b34e","modified":1660569854091},{"_id":"public/highlightjs/railscasts.css","hash":"aeb6ecd79552b9611d447fe56de5266954ea055c","modified":1660569854091},{"_id":"public/highlightjs/monokai.css","hash":"a0edb8327c191516a04d456db8aae9044055a5cf","modified":1660569854091},{"_id":"public/highlightjs/school_book.css","hash":"f257d41cdca2609fa4c664df9cc14b48e2bcb09f","modified":1660569854091},{"_id":"public/css/all.css","hash":"33cba693ed2007ee5119d0efd97cef9effe4d83d","modified":1660569854091},{"_id":"public/css/animsition.min.css","hash":"59033074f6594a0d87c759e2b8cf9baa3a62ed6a","modified":1660569854091},{"_id":"public/css/bootstrap.min.css","hash":"aabbadd6b436fa24c84fd8ca01d433bdab26fba5","modified":1660569854091},{"_id":"public/css/style.css","hash":"4b2f1e4d1e2ac78454691c7980b6e785979f4218","modified":1660569854091},{"_id":"public/fancybox/jquery.fancybox.pack.js","hash":"53360764b429c212f424399384417ccc233bb3be","modified":1660569854091},{"_id":"public/fonts/icons.svg","hash":"4b8357c608c01f304789e34bfd133081c1fc8b9d","modified":1660569854091},{"_id":"public/highlightjs/sunburst.css","hash":"e72bc116795505c1fcae35bc69045043fc34a243","modified":1660569854091},{"_id":"public/highlightjs/tomorrow-night-blue.css","hash":"e2bed22abcdf3f2b8ca3a1a73624751d3edc4e64","modified":1660569854091},{"_id":"public/highlightjs/solarized_dark.css","hash":"007f9f1e7addf7e2040734cd1f733d041432c335","modified":1660569854091},{"_id":"public/highlightjs/rainbow.css","hash":"b0e18f0f7fa08d5ad11956e2d9cc5e2ffdd514f3","modified":1660569854091},{"_id":"public/highlightjs/tomorrow-night-eighties.css","hash":"9603bc778de2dabd0ce1e7ee272a047338a8b99c","modified":1660569854091},{"_id":"public/highlightjs/tomorrow-night-bright.css","hash":"afdb004743a8d2b52d38c7a1fce32d631a0f3ded","modified":1660569854091},{"_id":"public/highlightjs/tomorrow-night.css","hash":"48cd18ce93daa491d89eb63e5fe3ab640ff56d74","modified":1660569854091},{"_id":"public/highlightjs/solarized_light.css","hash":"a85878fd70ecd03c71944df1acbbf320bac7979f","modified":1660569854091},{"_id":"public/highlightjs/tomorrow.css","hash":"a184e23b28b6a6401ecfc35e0a94de0bada589e4","modified":1660569854091},{"_id":"public/highlightjs/vs.css","hash":"13e2f7ec2e197d79f4fc36768ea4a0663d41e1c0","modified":1660569854091},{"_id":"public/highlightjs/xcode.css","hash":"78cb5758ce4085aa51edb6c5beb64d8f4511edd7","modified":1660569854091},{"_id":"public/js/html5shiv.min.js","hash":"bb51a5f6c394989bb06e4171179354c6d05ec8f8","modified":1660569854091},{"_id":"public/js/jquery.ajaxchimp.min.js","hash":"9be17785b0d816e1cd6bc45908e1805e0522fe18","modified":1660569854091},{"_id":"public/highlightjs/zenburn.css","hash":"73dafd21563f5fc3bb74856d4abf97c447a27772","modified":1660569854091},{"_id":"public/js/respond.min.js","hash":"b5aba40d65b0d6f85859db47f757ea971a0efd30","modified":1660569854091},{"_id":"public/js/scripts.js","hash":"9c05b2538f02df0313e6892083d2716d2c258f49","modified":1660569854091},{"_id":"public/js/jquery-1.11.1.min.js","hash":"d6c1f41972de07b09bfa63d2e50f9ab41ec372bd","modified":1660569854091},{"_id":"public/js/plugins.min.js","hash":"b9c5dd602b0d25d02ad704eef6e4e4d3b25f78db","modified":1660569854091},{"_id":"public/js/jquery.flexslider-min.js","hash":"51b3a7d882f438d53dc69ca5289e92254160c09a","modified":1660569854091},{"_id":"public/js/ziploader.js","hash":"f0266f9d8f5bd652ab5370fea02ac90401795ee2","modified":1660569854091},{"_id":"source/_posts/What-are-the-5-best-pet-grooming-services.md","hash":"790eeeaaebdad586ccd4cb50b895197082054cc2","modified":1663579888078},{"_id":"public/2022/09/19/What-are-the-5-best-pet-grooming-services/index.html","hash":"5091c4bac01c9635e6f7cfb74413447f7aefdd6a","modified":1663642483071},{"_id":"public/archives/2022/09/index.html","hash":"d71292bed994310726e1ef31e99c017ffddae59e","modified":1663642483071},{"_id":"public/categories/Dog-Grooming/index.html","hash":"baee56f3ddcbda668f94861c29ec35926022c02a","modified":1663642483071}],"Category":[{"name":"Dog Park","_id":"cl6usf09q0003pgv5041p9s2n"},{"name":"Dog Grooming","_id":"cl88kij480001s4v5hsbo7aj3"}],"Data":[],"Page":[{"title":"categories","date":"2022-08-15T13:23:40.000Z","type":"categories","layout":"categories","_content":"","source":"categories/index.md","raw":"---\ntitle: categories\ndate: 2022-08-15 21:23:40\ntype: \"categories\"\nlayout: \"categories\"\n---\n","updated":"2022-08-15T13:23:40.880Z","path":"categories/index.html","comments":1,"_id":"cl6usf09a0000pgv58msx6094","content":"","site":{"data":{}},"excerpt":"","more":""},{"title":"tags","date":"2022-08-15T13:23:43.000Z","type":"tags","layout":"tags","_content":"","source":"tags/index.md","raw":"---\ntitle: tags\ndate: 2022-08-15 21:23:43\ntype: \"tags\"\nlayout: \"tags\"\n---\n","updated":"2022-08-15T13:23:43.067Z","path":"tags/index.html","comments":1,"_id":"cl6usf09m0001pgv5g2qseh0h","content":"","site":{"data":{}},"excerpt":"","more":""}],"Post":[{"title":"What are the 10 easy ways to make your dog more comfortable at home","date":"2022-08-15T13:24:12.000Z","_content":"\n\n#  What are the 10 easy ways to make your dog more comfortable at home?\n\nYour dog is part of your family and you want to make sure they're as comfortable as possible in your home. Here are 10 easy ways to do just that:\n\n1. Make sure they have a comfortable place to sleep – whether it's a dog bed, blanket, or even a spot on the couch, make sure they have a designated spot where they can relax.\n\n2. Give them plenty of toys to chew on – dogs love to chew, so give them plenty of toys to keep them busy. This will also help keep their teeth healthy.\n\n3. Take them on walks – exercise is important for both dogs and humans, so take your pup for a walk each day.\n\n4. Let them run around in the yard – if you have a yard, let your dog run around and explore. This is great exercise for them and will tire them out.\n\n5. Feed them a good diet – feeding your dog quality food is essential for their health and happiness. Talk to your vet about what's the best diet for your pup.\n\n6. Keep their nails trimmed – if their nails get too long, they can become uncomfortable and even painful. Trim their nails regularly to avoid this issue.\n\n7.,8.,9.,10 See more tips at [website name or blog URL].\n\n#  Why is it important for dogs to be comfortable in their homes?\n\nThere’s no question that dogs are man’s best friend. They provide us with companionship, love, and security, and for many people, their dog is an important part of the family. It’s therefore important for dogs to feel comfortable in their homes.\n\nOne way to ensure your dog feels at ease in your home is by providing them with a designated space just for them. This could be a comfortable bed or couch in a quiet corner of the house where your dog can relax and feel safe. Another way to make your dog feel at ease is by ensuring that their food and water bowls are always clean and filled with fresh water. You should also provide your dog with plenty of toys to keep them occupied, such as chew toys, balls, and Frisbees.\n\nMost importantly, make sure you spend time with your dog. Play with them, take them for walks, and give them lots of attention. Dogs need interaction with their owners in order to feel loved and secure. By creating a comfortable environment for your dog and spending time with them on a regular basis, you’ll help make sure they always feel happy and at home in your family.\n\n#  How can you tell if your dog is uncomfortable in their home?\n\nOften times, dog owners will not realize their dog is uncomfortable until it’s too late. Dogs who are uncomfortable in their home may show signs of aggression, anxiety, or depression. If you think your dog may be uncomfortable, here are some tips on how to tell:\n\n§ One sign that a dog may be uncomfortable is if they are always licking their lips. This can be a sign of anxiety or stress.\n\n§ Another sign is if the dog has diarrhea or seems to be constantly having accidents in the house. This can often times be a sign of anxiety related to the environment.\n\n§ If the dog is barking or growling at family members or guests and seems agitated, this could also be a sign of discomfort.\n\n§ A dog that is consistently sleeping more than usual or hiding under furniture may also be trying to tell you something.\n\nIn order to help make your dog more comfortable in their home, there are a few things you can do. First, create a safe space for them where they can retreat to if they feel overwhelmed. This could be an enclosed area with its own bed and toys. Secondly, make sure there are plenty of positive reinforcement activities for your dog to do such as playing fetch or going for walks. Lastly, ensure that everyone in the household is following commands such as not petting the dog when they aren’t comfortable and not making sudden movements around them. By being proactive and paying attention to your dog’s body language, you can help make them more comfortable and avoid any unwanted behavior problems.\n\n#  What are some of the signs that your dog may be uncomfortable in their home?\n\nThere are a few signs that your dog may be uncomfortable in their home. One sign is that your dog may be restless and pace around the house. If your dog has started to eliminate in areas other than their designated potty spot, this could also be a sign of discomfort. If your dog is barking more than usual or showing any aggression towards family members or guests, this could mean that they are not feeling safe in their environment. If you have noticed any of these signs in your dog, it is important to consult with a professional trainer or behaviorist to help create a plan to make your dog more comfortable in their home.\n\n#  What can you do to help make your dog more comfortable in their home?\n\nThere are a few things you can do to help make your dog more comfortable in their home. One is to create a safe space for them, where they can retreat to if they feel scared or anxious. This could be a kennel or crate that they can go into voluntarily, or a designated spot on the floor or bed where they know they will be left alone. You can also provide them with plenty of toys and treats to keep them occupied, and schedule regular walks and playtime sessions so they get plenty of exercise and stimulation. If your dog is particularly anxious or fearful around other people or animals, consider enrolling them in a training class or using a muzzle when out in public. By taking these steps, you can help your furry friend feel more comfortable and secure in their home environment.","source":"_posts/What-are-the-10-easy-ways-to-make-your-dog-more-comfortable-at-home.md","raw":"---\ntitle: What are the 10 easy ways to make your dog more comfortable at home\ndate: 2022-08-15 21:24:12\ncategories:\n- Dog Park\ntags:\n---\n\n\n#  What are the 10 easy ways to make your dog more comfortable at home?\n\nYour dog is part of your family and you want to make sure they're as comfortable as possible in your home. Here are 10 easy ways to do just that:\n\n1. Make sure they have a comfortable place to sleep – whether it's a dog bed, blanket, or even a spot on the couch, make sure they have a designated spot where they can relax.\n\n2. Give them plenty of toys to chew on – dogs love to chew, so give them plenty of toys to keep them busy. This will also help keep their teeth healthy.\n\n3. Take them on walks – exercise is important for both dogs and humans, so take your pup for a walk each day.\n\n4. Let them run around in the yard – if you have a yard, let your dog run around and explore. This is great exercise for them and will tire them out.\n\n5. Feed them a good diet – feeding your dog quality food is essential for their health and happiness. Talk to your vet about what's the best diet for your pup.\n\n6. Keep their nails trimmed – if their nails get too long, they can become uncomfortable and even painful. Trim their nails regularly to avoid this issue.\n\n7.,8.,9.,10 See more tips at [website name or blog URL].\n\n#  Why is it important for dogs to be comfortable in their homes?\n\nThere’s no question that dogs are man’s best friend. They provide us with companionship, love, and security, and for many people, their dog is an important part of the family. It’s therefore important for dogs to feel comfortable in their homes.\n\nOne way to ensure your dog feels at ease in your home is by providing them with a designated space just for them. This could be a comfortable bed or couch in a quiet corner of the house where your dog can relax and feel safe. Another way to make your dog feel at ease is by ensuring that their food and water bowls are always clean and filled with fresh water. You should also provide your dog with plenty of toys to keep them occupied, such as chew toys, balls, and Frisbees.\n\nMost importantly, make sure you spend time with your dog. Play with them, take them for walks, and give them lots of attention. Dogs need interaction with their owners in order to feel loved and secure. By creating a comfortable environment for your dog and spending time with them on a regular basis, you’ll help make sure they always feel happy and at home in your family.\n\n#  How can you tell if your dog is uncomfortable in their home?\n\nOften times, dog owners will not realize their dog is uncomfortable until it’s too late. Dogs who are uncomfortable in their home may show signs of aggression, anxiety, or depression. If you think your dog may be uncomfortable, here are some tips on how to tell:\n\n§ One sign that a dog may be uncomfortable is if they are always licking their lips. This can be a sign of anxiety or stress.\n\n§ Another sign is if the dog has diarrhea or seems to be constantly having accidents in the house. This can often times be a sign of anxiety related to the environment.\n\n§ If the dog is barking or growling at family members or guests and seems agitated, this could also be a sign of discomfort.\n\n§ A dog that is consistently sleeping more than usual or hiding under furniture may also be trying to tell you something.\n\nIn order to help make your dog more comfortable in their home, there are a few things you can do. First, create a safe space for them where they can retreat to if they feel overwhelmed. This could be an enclosed area with its own bed and toys. Secondly, make sure there are plenty of positive reinforcement activities for your dog to do such as playing fetch or going for walks. Lastly, ensure that everyone in the household is following commands such as not petting the dog when they aren’t comfortable and not making sudden movements around them. By being proactive and paying attention to your dog’s body language, you can help make them more comfortable and avoid any unwanted behavior problems.\n\n#  What are some of the signs that your dog may be uncomfortable in their home?\n\nThere are a few signs that your dog may be uncomfortable in their home. One sign is that your dog may be restless and pace around the house. If your dog has started to eliminate in areas other than their designated potty spot, this could also be a sign of discomfort. If your dog is barking more than usual or showing any aggression towards family members or guests, this could mean that they are not feeling safe in their environment. If you have noticed any of these signs in your dog, it is important to consult with a professional trainer or behaviorist to help create a plan to make your dog more comfortable in their home.\n\n#  What can you do to help make your dog more comfortable in their home?\n\nThere are a few things you can do to help make your dog more comfortable in their home. One is to create a safe space for them, where they can retreat to if they feel scared or anxious. This could be a kennel or crate that they can go into voluntarily, or a designated spot on the floor or bed where they know they will be left alone. You can also provide them with plenty of toys and treats to keep them occupied, and schedule regular walks and playtime sessions so they get plenty of exercise and stimulation. If your dog is particularly anxious or fearful around other people or animals, consider enrolling them in a training class or using a muzzle when out in public. By taking these steps, you can help your furry friend feel more comfortable and secure in their home environment.","slug":"What-are-the-10-easy-ways-to-make-your-dog-more-comfortable-at-home","published":1,"updated":"2022-08-15T13:24:12.417Z","comments":1,"layout":"post","photos":[],"link":"","_id":"cl6usf09n0002pgv5apsf3ice","content":"<h1 id=\"What-are-the-10-easy-ways-to-make-your-dog-more-comfortable-at-home\"><a href=\"#What-are-the-10-easy-ways-to-make-your-dog-more-comfortable-at-home\" class=\"headerlink\" title=\"What are the 10 easy ways to make your dog more comfortable at home?\"></a>What are the 10 easy ways to make your dog more comfortable at home?</h1><p>Your dog is part of your family and you want to make sure they’re as comfortable as possible in your home. Here are 10 easy ways to do just that:</p>\n<ol>\n<li><p>Make sure they have a comfortable place to sleep – whether it’s a dog bed, blanket, or even a spot on the couch, make sure they have a designated spot where they can relax.</p>\n</li>\n<li><p>Give them plenty of toys to chew on – dogs love to chew, so give them plenty of toys to keep them busy. This will also help keep their teeth healthy.</p>\n</li>\n<li><p>Take them on walks – exercise is important for both dogs and humans, so take your pup for a walk each day.</p>\n</li>\n<li><p>Let them run around in the yard – if you have a yard, let your dog run around and explore. This is great exercise for them and will tire them out.</p>\n</li>\n<li><p>Feed them a good diet – feeding your dog quality food is essential for their health and happiness. Talk to your vet about what’s the best diet for your pup.</p>\n</li>\n<li><p>Keep their nails trimmed – if their nails get too long, they can become uncomfortable and even painful. Trim their nails regularly to avoid this issue.</p>\n</li>\n</ol>\n<p>7.,8.,9.,10 See more tips at [website name or blog URL].</p>\n<h1 id=\"Why-is-it-important-for-dogs-to-be-comfortable-in-their-homes\"><a href=\"#Why-is-it-important-for-dogs-to-be-comfortable-in-their-homes\" class=\"headerlink\" title=\"Why is it important for dogs to be comfortable in their homes?\"></a>Why is it important for dogs to be comfortable in their homes?</h1><p>There’s no question that dogs are man’s best friend. They provide us with companionship, love, and security, and for many people, their dog is an important part of the family. It’s therefore important for dogs to feel comfortable in their homes.</p>\n<p>One way to ensure your dog feels at ease in your home is by providing them with a designated space just for them. This could be a comfortable bed or couch in a quiet corner of the house where your dog can relax and feel safe. Another way to make your dog feel at ease is by ensuring that their food and water bowls are always clean and filled with fresh water. You should also provide your dog with plenty of toys to keep them occupied, such as chew toys, balls, and Frisbees.</p>\n<p>Most importantly, make sure you spend time with your dog. Play with them, take them for walks, and give them lots of attention. Dogs need interaction with their owners in order to feel loved and secure. By creating a comfortable environment for your dog and spending time with them on a regular basis, you’ll help make sure they always feel happy and at home in your family.</p>\n<h1 id=\"How-can-you-tell-if-your-dog-is-uncomfortable-in-their-home\"><a href=\"#How-can-you-tell-if-your-dog-is-uncomfortable-in-their-home\" class=\"headerlink\" title=\"How can you tell if your dog is uncomfortable in their home?\"></a>How can you tell if your dog is uncomfortable in their home?</h1><p>Often times, dog owners will not realize their dog is uncomfortable until it’s too late. Dogs who are uncomfortable in their home may show signs of aggression, anxiety, or depression. If you think your dog may be uncomfortable, here are some tips on how to tell:</p>\n<p>§ One sign that a dog may be uncomfortable is if they are always licking their lips. This can be a sign of anxiety or stress.</p>\n<p>§ Another sign is if the dog has diarrhea or seems to be constantly having accidents in the house. This can often times be a sign of anxiety related to the environment.</p>\n<p>§ If the dog is barking or growling at family members or guests and seems agitated, this could also be a sign of discomfort.</p>\n<p>§ A dog that is consistently sleeping more than usual or hiding under furniture may also be trying to tell you something.</p>\n<p>In order to help make your dog more comfortable in their home, there are a few things you can do. First, create a safe space for them where they can retreat to if they feel overwhelmed. This could be an enclosed area with its own bed and toys. Secondly, make sure there are plenty of positive reinforcement activities for your dog to do such as playing fetch or going for walks. Lastly, ensure that everyone in the household is following commands such as not petting the dog when they aren’t comfortable and not making sudden movements around them. By being proactive and paying attention to your dog’s body language, you can help make them more comfortable and avoid any unwanted behavior problems.</p>\n<h1 id=\"What-are-some-of-the-signs-that-your-dog-may-be-uncomfortable-in-their-home\"><a href=\"#What-are-some-of-the-signs-that-your-dog-may-be-uncomfortable-in-their-home\" class=\"headerlink\" title=\"What are some of the signs that your dog may be uncomfortable in their home?\"></a>What are some of the signs that your dog may be uncomfortable in their home?</h1><p>There are a few signs that your dog may be uncomfortable in their home. One sign is that your dog may be restless and pace around the house. If your dog has started to eliminate in areas other than their designated potty spot, this could also be a sign of discomfort. If your dog is barking more than usual or showing any aggression towards family members or guests, this could mean that they are not feeling safe in their environment. If you have noticed any of these signs in your dog, it is important to consult with a professional trainer or behaviorist to help create a plan to make your dog more comfortable in their home.</p>\n<h1 id=\"What-can-you-do-to-help-make-your-dog-more-comfortable-in-their-home\"><a href=\"#What-can-you-do-to-help-make-your-dog-more-comfortable-in-their-home\" class=\"headerlink\" title=\"What can you do to help make your dog more comfortable in their home?\"></a>What can you do to help make your dog more comfortable in their home?</h1><p>There are a few things you can do to help make your dog more comfortable in their home. One is to create a safe space for them, where they can retreat to if they feel scared or anxious. This could be a kennel or crate that they can go into voluntarily, or a designated spot on the floor or bed where they know they will be left alone. You can also provide them with plenty of toys and treats to keep them occupied, and schedule regular walks and playtime sessions so they get plenty of exercise and stimulation. If your dog is particularly anxious or fearful around other people or animals, consider enrolling them in a training class or using a muzzle when out in public. By taking these steps, you can help your furry friend feel more comfortable and secure in their home environment.</p>\n","site":{"data":{}},"excerpt":"","more":"<h1 id=\"What-are-the-10-easy-ways-to-make-your-dog-more-comfortable-at-home\"><a href=\"#What-are-the-10-easy-ways-to-make-your-dog-more-comfortable-at-home\" class=\"headerlink\" title=\"What are the 10 easy ways to make your dog more comfortable at home?\"></a>What are the 10 easy ways to make your dog more comfortable at home?</h1><p>Your dog is part of your family and you want to make sure they’re as comfortable as possible in your home. Here are 10 easy ways to do just that:</p>\n<ol>\n<li><p>Make sure they have a comfortable place to sleep – whether it’s a dog bed, blanket, or even a spot on the couch, make sure they have a designated spot where they can relax.</p>\n</li>\n<li><p>Give them plenty of toys to chew on – dogs love to chew, so give them plenty of toys to keep them busy. This will also help keep their teeth healthy.</p>\n</li>\n<li><p>Take them on walks – exercise is important for both dogs and humans, so take your pup for a walk each day.</p>\n</li>\n<li><p>Let them run around in the yard – if you have a yard, let your dog run around and explore. This is great exercise for them and will tire them out.</p>\n</li>\n<li><p>Feed them a good diet – feeding your dog quality food is essential for their health and happiness. Talk to your vet about what’s the best diet for your pup.</p>\n</li>\n<li><p>Keep their nails trimmed – if their nails get too long, they can become uncomfortable and even painful. Trim their nails regularly to avoid this issue.</p>\n</li>\n</ol>\n<p>7.,8.,9.,10 See more tips at [website name or blog URL].</p>\n<h1 id=\"Why-is-it-important-for-dogs-to-be-comfortable-in-their-homes\"><a href=\"#Why-is-it-important-for-dogs-to-be-comfortable-in-their-homes\" class=\"headerlink\" title=\"Why is it important for dogs to be comfortable in their homes?\"></a>Why is it important for dogs to be comfortable in their homes?</h1><p>There’s no question that dogs are man’s best friend. They provide us with companionship, love, and security, and for many people, their dog is an important part of the family. It’s therefore important for dogs to feel comfortable in their homes.</p>\n<p>One way to ensure your dog feels at ease in your home is by providing them with a designated space just for them. This could be a comfortable bed or couch in a quiet corner of the house where your dog can relax and feel safe. Another way to make your dog feel at ease is by ensuring that their food and water bowls are always clean and filled with fresh water. You should also provide your dog with plenty of toys to keep them occupied, such as chew toys, balls, and Frisbees.</p>\n<p>Most importantly, make sure you spend time with your dog. Play with them, take them for walks, and give them lots of attention. Dogs need interaction with their owners in order to feel loved and secure. By creating a comfortable environment for your dog and spending time with them on a regular basis, you’ll help make sure they always feel happy and at home in your family.</p>\n<h1 id=\"How-can-you-tell-if-your-dog-is-uncomfortable-in-their-home\"><a href=\"#How-can-you-tell-if-your-dog-is-uncomfortable-in-their-home\" class=\"headerlink\" title=\"How can you tell if your dog is uncomfortable in their home?\"></a>How can you tell if your dog is uncomfortable in their home?</h1><p>Often times, dog owners will not realize their dog is uncomfortable until it’s too late. Dogs who are uncomfortable in their home may show signs of aggression, anxiety, or depression. If you think your dog may be uncomfortable, here are some tips on how to tell:</p>\n<p>§ One sign that a dog may be uncomfortable is if they are always licking their lips. This can be a sign of anxiety or stress.</p>\n<p>§ Another sign is if the dog has diarrhea or seems to be constantly having accidents in the house. This can often times be a sign of anxiety related to the environment.</p>\n<p>§ If the dog is barking or growling at family members or guests and seems agitated, this could also be a sign of discomfort.</p>\n<p>§ A dog that is consistently sleeping more than usual or hiding under furniture may also be trying to tell you something.</p>\n<p>In order to help make your dog more comfortable in their home, there are a few things you can do. First, create a safe space for them where they can retreat to if they feel overwhelmed. This could be an enclosed area with its own bed and toys. Secondly, make sure there are plenty of positive reinforcement activities for your dog to do such as playing fetch or going for walks. Lastly, ensure that everyone in the household is following commands such as not petting the dog when they aren’t comfortable and not making sudden movements around them. By being proactive and paying attention to your dog’s body language, you can help make them more comfortable and avoid any unwanted behavior problems.</p>\n<h1 id=\"What-are-some-of-the-signs-that-your-dog-may-be-uncomfortable-in-their-home\"><a href=\"#What-are-some-of-the-signs-that-your-dog-may-be-uncomfortable-in-their-home\" class=\"headerlink\" title=\"What are some of the signs that your dog may be uncomfortable in their home?\"></a>What are some of the signs that your dog may be uncomfortable in their home?</h1><p>There are a few signs that your dog may be uncomfortable in their home. One sign is that your dog may be restless and pace around the house. If your dog has started to eliminate in areas other than their designated potty spot, this could also be a sign of discomfort. If your dog is barking more than usual or showing any aggression towards family members or guests, this could mean that they are not feeling safe in their environment. If you have noticed any of these signs in your dog, it is important to consult with a professional trainer or behaviorist to help create a plan to make your dog more comfortable in their home.</p>\n<h1 id=\"What-can-you-do-to-help-make-your-dog-more-comfortable-in-their-home\"><a href=\"#What-can-you-do-to-help-make-your-dog-more-comfortable-in-their-home\" class=\"headerlink\" title=\"What can you do to help make your dog more comfortable in their home?\"></a>What can you do to help make your dog more comfortable in their home?</h1><p>There are a few things you can do to help make your dog more comfortable in their home. One is to create a safe space for them, where they can retreat to if they feel scared or anxious. This could be a kennel or crate that they can go into voluntarily, or a designated spot on the floor or bed where they know they will be left alone. You can also provide them with plenty of toys and treats to keep them occupied, and schedule regular walks and playtime sessions so they get plenty of exercise and stimulation. If your dog is particularly anxious or fearful around other people or animals, consider enrolling them in a training class or using a muzzle when out in public. By taking these steps, you can help your furry friend feel more comfortable and secure in their home environment.</p>\n"},{"title":"What are the 5 best pet grooming services","date":"2022-09-19T09:31:28.000Z","_content":"\n\n#  What are the 5 best pet grooming services?\n\nThere are many pet grooming services available, so it can be difficult to decide which one is the best for your pet. Here are five of the best.\n\n1. PetSmart Grooming\n\nPetSmart is a national chain of pet stores and groomers. They offer a wide range of services, including haircuts, baths, nail trims, and ear cleanings. Pets are groomed by professional stylists who have been certified by the American Kennel Club.\n\n2. The Groomery\n\nThe Groomery is a Los Angeles-based pet grooming service that offers everything from basic haircuts to full spa packages. They use all natural shampoos and conditioners, and they only use blades, no scissors, to avoid nicking your pet's skin.\n\n3. Bow Wow Dog Grooming\n\nBow Wow Dog Grooming is a small, family-owned business that offers personal attention to each dog they groom. They use high-quality products and offer a variety of services, including haircuts, baths, and anal gland expression.\n\n4. Pawsitively Pretty Grooming Salon\n\nPawsitively Pretty Grooming Salon offers a wide range of services for both dogs and cats. Services include haircuts, baths, flea treatments, ear cleaning, and anal glandexpression. They use all natural products and work only with experienced groomers who love animals.\n\n5. The Dogfather Mobile Pet Grooming Service\n\nThe Dogfather Mobile Pet Grooming Service is a mobile grooming service that comes to your home to groom your pet. This is a great option if you live in a rural area or if your pet hates going to the groomer's shop. Services include haircuts, baths, nail trimming, and ears cleaning.\n\n#  What do these services offer?\n\nMost of these services offer online backup, disaster recovery, and business continuity.\n\n# What are the benefits of using these services?\n\nThere are several benefits to using these services. They include:\n\n-Peace of mind: knowing your data is safe and can be recovered in the event of a disaster.\n\n-Efficient and reliable data backups: having an offsite backup will ensure your data is available even if your primary site is unavailable.\n\n-Reduced downtime and business interruption: in the event of a disaster, you can resume operations quickly by using the service’s cloud infrastructure.\n\n#  How much do they cost?\n\nPrices for chickens vary depending on the breed of chicken. You can expect to pay anywhere from $2-$10 per chicken. Some especially rare or specialized breeds can cost much more.\n\nHens that are used for egg-laying tend to be more expensive than meat chickens, and the prices can vary depending on the area you live in. In general, you can expect to pay around $5-$25 for a laying hen, depending on her age, quality, and breed.\n\nChickens that are being sold as chicks generally cost less than fully grown chickens. Most people spend around $0.50-$3 per chick, depending on the breed.\n\nIf you are interested in hatching your own chicks, you will need to purchase an incubator and fertile eggs. The incubator will cost around $60-100 and fertile eggs cost around $2-5 per dozen.\n\n#  What is the quality of their services?\n\n#\n\nThe quality of service is a key factor to consider when choosing a web hosting company. You want to be sure that the company you choose will be there for you when you need them. The quality of service can vary from one company to another, so it is important to do your research before selecting a host.\n\n# How reliable are their servers?\n\nReliability is another important factor to consider when choosing a web hosting company. You want to make sure that the company's servers are reliable and that your website will be up and running at all times. This is especially important if your website is your business and you rely on it to generate income.\n\n# What kind of support do they offer?\n\nIt is also important to consider the level of support that the web hosting company offers. You want to be sure that they are available 24/7 in case of emergencies. They should also have a robust Knowledge Base with answers to common questions so that you can solve most problems on your own.\n\n# What kind of features do they offer?\n\nMany web hosting companies offer a wide range of features, including domain registration, e-commerce capabilities, and unlimited storage and bandwidth. Make sure the company you choose offers the features you need to run your website successfully.\n\n#  Why should I choose one of these services over another?\n\nThis is a question that is often asked by people who are looking for a new cell phone service. There are many different services to choose from, and it can be hard to decide which one is the best for you. In this article, we will compare three of the most popular cell phone services: AT&T, Verizon, and Sprint.\n\nWe will start by looking at the coverage area for each service. AT&T has the largest coverage area, followed by Verizon and then Sprint. This means that if you live in a rural area, AT&T is probably your best option. If you live in a city, Verizon or AT&T would be good choices. Sprint has the smallest coverage area, so it is not a good choice if you live in a rural area.\n\nNext, we will look at the price of each service. AT&T is the most expensive, followed by Verizon and then Sprint. This means that if price is important to you, Verizon would be your best choice.\n\nFinally, we will look at the customer service ratings for each service. AT&T has the highest ratings, followed by Verizon and then Sprint. This means that if you are looking for great customer service, AT&T would be your best choice.","source":"_posts/What-are-the-5-best-pet-grooming-services.md","raw":"---\ntitle: What are the 5 best pet grooming services\ndate: 2022-09-19 17:31:28\ncategories:\n- Dog Grooming\ntags:\n---\n\n\n#  What are the 5 best pet grooming services?\n\nThere are many pet grooming services available, so it can be difficult to decide which one is the best for your pet. Here are five of the best.\n\n1. PetSmart Grooming\n\nPetSmart is a national chain of pet stores and groomers. They offer a wide range of services, including haircuts, baths, nail trims, and ear cleanings. Pets are groomed by professional stylists who have been certified by the American Kennel Club.\n\n2. The Groomery\n\nThe Groomery is a Los Angeles-based pet grooming service that offers everything from basic haircuts to full spa packages. They use all natural shampoos and conditioners, and they only use blades, no scissors, to avoid nicking your pet's skin.\n\n3. Bow Wow Dog Grooming\n\nBow Wow Dog Grooming is a small, family-owned business that offers personal attention to each dog they groom. They use high-quality products and offer a variety of services, including haircuts, baths, and anal gland expression.\n\n4. Pawsitively Pretty Grooming Salon\n\nPawsitively Pretty Grooming Salon offers a wide range of services for both dogs and cats. Services include haircuts, baths, flea treatments, ear cleaning, and anal glandexpression. They use all natural products and work only with experienced groomers who love animals.\n\n5. The Dogfather Mobile Pet Grooming Service\n\nThe Dogfather Mobile Pet Grooming Service is a mobile grooming service that comes to your home to groom your pet. This is a great option if you live in a rural area or if your pet hates going to the groomer's shop. Services include haircuts, baths, nail trimming, and ears cleaning.\n\n#  What do these services offer?\n\nMost of these services offer online backup, disaster recovery, and business continuity.\n\n# What are the benefits of using these services?\n\nThere are several benefits to using these services. They include:\n\n-Peace of mind: knowing your data is safe and can be recovered in the event of a disaster.\n\n-Efficient and reliable data backups: having an offsite backup will ensure your data is available even if your primary site is unavailable.\n\n-Reduced downtime and business interruption: in the event of a disaster, you can resume operations quickly by using the service’s cloud infrastructure.\n\n#  How much do they cost?\n\nPrices for chickens vary depending on the breed of chicken. You can expect to pay anywhere from $2-$10 per chicken. Some especially rare or specialized breeds can cost much more.\n\nHens that are used for egg-laying tend to be more expensive than meat chickens, and the prices can vary depending on the area you live in. In general, you can expect to pay around $5-$25 for a laying hen, depending on her age, quality, and breed.\n\nChickens that are being sold as chicks generally cost less than fully grown chickens. Most people spend around $0.50-$3 per chick, depending on the breed.\n\nIf you are interested in hatching your own chicks, you will need to purchase an incubator and fertile eggs. The incubator will cost around $60-100 and fertile eggs cost around $2-5 per dozen.\n\n#  What is the quality of their services?\n\n#\n\nThe quality of service is a key factor to consider when choosing a web hosting company. You want to be sure that the company you choose will be there for you when you need them. The quality of service can vary from one company to another, so it is important to do your research before selecting a host.\n\n# How reliable are their servers?\n\nReliability is another important factor to consider when choosing a web hosting company. You want to make sure that the company's servers are reliable and that your website will be up and running at all times. This is especially important if your website is your business and you rely on it to generate income.\n\n# What kind of support do they offer?\n\nIt is also important to consider the level of support that the web hosting company offers. You want to be sure that they are available 24/7 in case of emergencies. They should also have a robust Knowledge Base with answers to common questions so that you can solve most problems on your own.\n\n# What kind of features do they offer?\n\nMany web hosting companies offer a wide range of features, including domain registration, e-commerce capabilities, and unlimited storage and bandwidth. Make sure the company you choose offers the features you need to run your website successfully.\n\n#  Why should I choose one of these services over another?\n\nThis is a question that is often asked by people who are looking for a new cell phone service. There are many different services to choose from, and it can be hard to decide which one is the best for you. In this article, we will compare three of the most popular cell phone services: AT&T, Verizon, and Sprint.\n\nWe will start by looking at the coverage area for each service. AT&T has the largest coverage area, followed by Verizon and then Sprint. This means that if you live in a rural area, AT&T is probably your best option. If you live in a city, Verizon or AT&T would be good choices. Sprint has the smallest coverage area, so it is not a good choice if you live in a rural area.\n\nNext, we will look at the price of each service. AT&T is the most expensive, followed by Verizon and then Sprint. This means that if price is important to you, Verizon would be your best choice.\n\nFinally, we will look at the customer service ratings for each service. AT&T has the highest ratings, followed by Verizon and then Sprint. This means that if you are looking for great customer service, AT&T would be your best choice.","slug":"What-are-the-5-best-pet-grooming-services","published":1,"updated":"2022-09-19T09:31:28.078Z","comments":1,"layout":"post","photos":[],"link":"","_id":"cl88kij3z0000s4v57vr0hygh","content":"<h1 id=\"What-are-the-5-best-pet-grooming-services\"><a href=\"#What-are-the-5-best-pet-grooming-services\" class=\"headerlink\" title=\"What are the 5 best pet grooming services?\"></a>What are the 5 best pet grooming services?</h1><p>There are many pet grooming services available, so it can be difficult to decide which one is the best for your pet. Here are five of the best.</p>\n<ol>\n<li>PetSmart Grooming</li>\n</ol>\n<p>PetSmart is a national chain of pet stores and groomers. They offer a wide range of services, including haircuts, baths, nail trims, and ear cleanings. Pets are groomed by professional stylists who have been certified by the American Kennel Club.</p>\n<ol start=\"2\">\n<li>The Groomery</li>\n</ol>\n<p>The Groomery is a Los Angeles-based pet grooming service that offers everything from basic haircuts to full spa packages. They use all natural shampoos and conditioners, and they only use blades, no scissors, to avoid nicking your pet’s skin.</p>\n<ol start=\"3\">\n<li>Bow Wow Dog Grooming</li>\n</ol>\n<p>Bow Wow Dog Grooming is a small, family-owned business that offers personal attention to each dog they groom. They use high-quality products and offer a variety of services, including haircuts, baths, and anal gland expression.</p>\n<ol start=\"4\">\n<li>Pawsitively Pretty Grooming Salon</li>\n</ol>\n<p>Pawsitively Pretty Grooming Salon offers a wide range of services for both dogs and cats. Services include haircuts, baths, flea treatments, ear cleaning, and anal glandexpression. They use all natural products and work only with experienced groomers who love animals.</p>\n<ol start=\"5\">\n<li>The Dogfather Mobile Pet Grooming Service</li>\n</ol>\n<p>The Dogfather Mobile Pet Grooming Service is a mobile grooming service that comes to your home to groom your pet. This is a great option if you live in a rural area or if your pet hates going to the groomer’s shop. Services include haircuts, baths, nail trimming, and ears cleaning.</p>\n<h1 id=\"What-do-these-services-offer\"><a href=\"#What-do-these-services-offer\" class=\"headerlink\" title=\"What do these services offer?\"></a>What do these services offer?</h1><p>Most of these services offer online backup, disaster recovery, and business continuity.</p>\n<h1 id=\"What-are-the-benefits-of-using-these-services\"><a href=\"#What-are-the-benefits-of-using-these-services\" class=\"headerlink\" title=\"What are the benefits of using these services?\"></a>What are the benefits of using these services?</h1><p>There are several benefits to using these services. They include:</p>\n<p>-Peace of mind: knowing your data is safe and can be recovered in the event of a disaster.</p>\n<p>-Efficient and reliable data backups: having an offsite backup will ensure your data is available even if your primary site is unavailable.</p>\n<p>-Reduced downtime and business interruption: in the event of a disaster, you can resume operations quickly by using the service’s cloud infrastructure.</p>\n<h1 id=\"How-much-do-they-cost\"><a href=\"#How-much-do-they-cost\" class=\"headerlink\" title=\"How much do they cost?\"></a>How much do they cost?</h1><p>Prices for chickens vary depending on the breed of chicken. You can expect to pay anywhere from $2-$10 per chicken. Some especially rare or specialized breeds can cost much more.</p>\n<p>Hens that are used for egg-laying tend to be more expensive than meat chickens, and the prices can vary depending on the area you live in. In general, you can expect to pay around $5-$25 for a laying hen, depending on her age, quality, and breed.</p>\n<p>Chickens that are being sold as chicks generally cost less than fully grown chickens. Most people spend around $0.50-$3 per chick, depending on the breed.</p>\n<p>If you are interested in hatching your own chicks, you will need to purchase an incubator and fertile eggs. The incubator will cost around $60-100 and fertile eggs cost around $2-5 per dozen.</p>\n<h1 id=\"What-is-the-quality-of-their-services\"><a href=\"#What-is-the-quality-of-their-services\" class=\"headerlink\" title=\"What is the quality of their services?\"></a>What is the quality of their services?</h1><h1 id=\"\"><a href=\"#\" class=\"headerlink\" title=\"\"></a></h1><p>The quality of service is a key factor to consider when choosing a web hosting company. You want to be sure that the company you choose will be there for you when you need them. The quality of service can vary from one company to another, so it is important to do your research before selecting a host.</p>\n<h1 id=\"How-reliable-are-their-servers\"><a href=\"#How-reliable-are-their-servers\" class=\"headerlink\" title=\"How reliable are their servers?\"></a>How reliable are their servers?</h1><p>Reliability is another important factor to consider when choosing a web hosting company. You want to make sure that the company’s servers are reliable and that your website will be up and running at all times. This is especially important if your website is your business and you rely on it to generate income.</p>\n<h1 id=\"What-kind-of-support-do-they-offer\"><a href=\"#What-kind-of-support-do-they-offer\" class=\"headerlink\" title=\"What kind of support do they offer?\"></a>What kind of support do they offer?</h1><p>It is also important to consider the level of support that the web hosting company offers. You want to be sure that they are available 24&#x2F;7 in case of emergencies. They should also have a robust Knowledge Base with answers to common questions so that you can solve most problems on your own.</p>\n<h1 id=\"What-kind-of-features-do-they-offer\"><a href=\"#What-kind-of-features-do-they-offer\" class=\"headerlink\" title=\"What kind of features do they offer?\"></a>What kind of features do they offer?</h1><p>Many web hosting companies offer a wide range of features, including domain registration, e-commerce capabilities, and unlimited storage and bandwidth. Make sure the company you choose offers the features you need to run your website successfully.</p>\n<h1 id=\"Why-should-I-choose-one-of-these-services-over-another\"><a href=\"#Why-should-I-choose-one-of-these-services-over-another\" class=\"headerlink\" title=\"Why should I choose one of these services over another?\"></a>Why should I choose one of these services over another?</h1><p>This is a question that is often asked by people who are looking for a new cell phone service. There are many different services to choose from, and it can be hard to decide which one is the best for you. In this article, we will compare three of the most popular cell phone services: AT&amp;T, Verizon, and Sprint.</p>\n<p>We will start by looking at the coverage area for each service. AT&amp;T has the largest coverage area, followed by Verizon and then Sprint. This means that if you live in a rural area, AT&amp;T is probably your best option. If you live in a city, Verizon or AT&amp;T would be good choices. Sprint has the smallest coverage area, so it is not a good choice if you live in a rural area.</p>\n<p>Next, we will look at the price of each service. AT&amp;T is the most expensive, followed by Verizon and then Sprint. This means that if price is important to you, Verizon would be your best choice.</p>\n<p>Finally, we will look at the customer service ratings for each service. AT&amp;T has the highest ratings, followed by Verizon and then Sprint. This means that if you are looking for great customer service, AT&amp;T would be your best choice.</p>\n","site":{"data":{}},"excerpt":"","more":"<h1 id=\"What-are-the-5-best-pet-grooming-services\"><a href=\"#What-are-the-5-best-pet-grooming-services\" class=\"headerlink\" title=\"What are the 5 best pet grooming services?\"></a>What are the 5 best pet grooming services?</h1><p>There are many pet grooming services available, so it can be difficult to decide which one is the best for your pet. Here are five of the best.</p>\n<ol>\n<li>PetSmart Grooming</li>\n</ol>\n<p>PetSmart is a national chain of pet stores and groomers. They offer a wide range of services, including haircuts, baths, nail trims, and ear cleanings. Pets are groomed by professional stylists who have been certified by the American Kennel Club.</p>\n<ol start=\"2\">\n<li>The Groomery</li>\n</ol>\n<p>The Groomery is a Los Angeles-based pet grooming service that offers everything from basic haircuts to full spa packages. They use all natural shampoos and conditioners, and they only use blades, no scissors, to avoid nicking your pet’s skin.</p>\n<ol start=\"3\">\n<li>Bow Wow Dog Grooming</li>\n</ol>\n<p>Bow Wow Dog Grooming is a small, family-owned business that offers personal attention to each dog they groom. They use high-quality products and offer a variety of services, including haircuts, baths, and anal gland expression.</p>\n<ol start=\"4\">\n<li>Pawsitively Pretty Grooming Salon</li>\n</ol>\n<p>Pawsitively Pretty Grooming Salon offers a wide range of services for both dogs and cats. Services include haircuts, baths, flea treatments, ear cleaning, and anal glandexpression. They use all natural products and work only with experienced groomers who love animals.</p>\n<ol start=\"5\">\n<li>The Dogfather Mobile Pet Grooming Service</li>\n</ol>\n<p>The Dogfather Mobile Pet Grooming Service is a mobile grooming service that comes to your home to groom your pet. This is a great option if you live in a rural area or if your pet hates going to the groomer’s shop. Services include haircuts, baths, nail trimming, and ears cleaning.</p>\n<h1 id=\"What-do-these-services-offer\"><a href=\"#What-do-these-services-offer\" class=\"headerlink\" title=\"What do these services offer?\"></a>What do these services offer?</h1><p>Most of these services offer online backup, disaster recovery, and business continuity.</p>\n<h1 id=\"What-are-the-benefits-of-using-these-services\"><a href=\"#What-are-the-benefits-of-using-these-services\" class=\"headerlink\" title=\"What are the benefits of using these services?\"></a>What are the benefits of using these services?</h1><p>There are several benefits to using these services. They include:</p>\n<p>-Peace of mind: knowing your data is safe and can be recovered in the event of a disaster.</p>\n<p>-Efficient and reliable data backups: having an offsite backup will ensure your data is available even if your primary site is unavailable.</p>\n<p>-Reduced downtime and business interruption: in the event of a disaster, you can resume operations quickly by using the service’s cloud infrastructure.</p>\n<h1 id=\"How-much-do-they-cost\"><a href=\"#How-much-do-they-cost\" class=\"headerlink\" title=\"How much do they cost?\"></a>How much do they cost?</h1><p>Prices for chickens vary depending on the breed of chicken. You can expect to pay anywhere from $2-$10 per chicken. Some especially rare or specialized breeds can cost much more.</p>\n<p>Hens that are used for egg-laying tend to be more expensive than meat chickens, and the prices can vary depending on the area you live in. In general, you can expect to pay around $5-$25 for a laying hen, depending on her age, quality, and breed.</p>\n<p>Chickens that are being sold as chicks generally cost less than fully grown chickens. Most people spend around $0.50-$3 per chick, depending on the breed.</p>\n<p>If you are interested in hatching your own chicks, you will need to purchase an incubator and fertile eggs. The incubator will cost around $60-100 and fertile eggs cost around $2-5 per dozen.</p>\n<h1 id=\"What-is-the-quality-of-their-services\"><a href=\"#What-is-the-quality-of-their-services\" class=\"headerlink\" title=\"What is the quality of their services?\"></a>What is the quality of their services?</h1><h1 id=\"\"><a href=\"#\" class=\"headerlink\" title=\"\"></a></h1><p>The quality of service is a key factor to consider when choosing a web hosting company. You want to be sure that the company you choose will be there for you when you need them. The quality of service can vary from one company to another, so it is important to do your research before selecting a host.</p>\n<h1 id=\"How-reliable-are-their-servers\"><a href=\"#How-reliable-are-their-servers\" class=\"headerlink\" title=\"How reliable are their servers?\"></a>How reliable are their servers?</h1><p>Reliability is another important factor to consider when choosing a web hosting company. You want to make sure that the company’s servers are reliable and that your website will be up and running at all times. This is especially important if your website is your business and you rely on it to generate income.</p>\n<h1 id=\"What-kind-of-support-do-they-offer\"><a href=\"#What-kind-of-support-do-they-offer\" class=\"headerlink\" title=\"What kind of support do they offer?\"></a>What kind of support do they offer?</h1><p>It is also important to consider the level of support that the web hosting company offers. You want to be sure that they are available 24&#x2F;7 in case of emergencies. They should also have a robust Knowledge Base with answers to common questions so that you can solve most problems on your own.</p>\n<h1 id=\"What-kind-of-features-do-they-offer\"><a href=\"#What-kind-of-features-do-they-offer\" class=\"headerlink\" title=\"What kind of features do they offer?\"></a>What kind of features do they offer?</h1><p>Many web hosting companies offer a wide range of features, including domain registration, e-commerce capabilities, and unlimited storage and bandwidth. Make sure the company you choose offers the features you need to run your website successfully.</p>\n<h1 id=\"Why-should-I-choose-one-of-these-services-over-another\"><a href=\"#Why-should-I-choose-one-of-these-services-over-another\" class=\"headerlink\" title=\"Why should I choose one of these services over another?\"></a>Why should I choose one of these services over another?</h1><p>This is a question that is often asked by people who are looking for a new cell phone service. There are many different services to choose from, and it can be hard to decide which one is the best for you. In this article, we will compare three of the most popular cell phone services: AT&amp;T, Verizon, and Sprint.</p>\n<p>We will start by looking at the coverage area for each service. AT&amp;T has the largest coverage area, followed by Verizon and then Sprint. This means that if you live in a rural area, AT&amp;T is probably your best option. If you live in a city, Verizon or AT&amp;T would be good choices. Sprint has the smallest coverage area, so it is not a good choice if you live in a rural area.</p>\n<p>Next, we will look at the price of each service. AT&amp;T is the most expensive, followed by Verizon and then Sprint. This means that if price is important to you, Verizon would be your best choice.</p>\n<p>Finally, we will look at the customer service ratings for each service. AT&amp;T has the highest ratings, followed by Verizon and then Sprint. This means that if you are looking for great customer service, AT&amp;T would be your best choice.</p>\n"}],"PostAsset":[],"PostCategory":[{"post_id":"cl6usf09n0002pgv5apsf3ice","category_id":"cl6usf09q0003pgv5041p9s2n","_id":"cl6usf09s0004pgv5dnyb2f9v"},{"post_id":"cl88kij3z0000s4v57vr0hygh","category_id":"cl88kij480001s4v5hsbo7aj3","_id":"cl88kij4b0002s4v582gx8ild"}],"PostTag":[],"Tag":[]}}